foonathan_memory_vendor/_dummy.cpython-314-x86_64-linux-gnu.so
ros_foonathan_memory_vendor-1.3.1.data/data/bin/nodesize_dbg
ros_foonathan_memory_vendor-1.3.1.data/data/include/foonathan_memory/foonathan/memory/aligned_allocator.hpp
ros_foonathan_memory_vendor-1.3.1.data/data/include/foonathan_memory/foonathan/memory/allocator_storage.hpp
ros_foonathan_memory_vendor-1.3.1.data/data/include/foonathan_memory/foonathan/memory/allocator_traits.hpp
ros_foonathan_memory_vendor-1.3.1.data/data/include/foonathan_memory/foonathan/memory/config.hpp
ros_foonathan_memory_vendor-1.3.1.data/data/include/foonathan_memory/foonathan/memory/config_impl.hpp
ros_foonathan_memory_vendor-1.3.1.data/data/include/foonathan_memory/foonathan/memory/container.hpp
ros_foonathan_memory_vendor-1.3.1.data/data/include/foonathan_memory/foonathan/memory/container_node_sizes_impl.hpp
ros_foonathan_memory_vendor-1.3.1.data/data/include/foonathan_memory/foonathan/memory/debugging.hpp
ros_foonathan_memory_vendor-1.3.1.data/data/include/foonathan_memory/foonathan/memory/default_allocator.hpp
ros_foonathan_memory_vendor-1.3.1.data/data/include/foonathan_memory/foonathan/memory/deleter.hpp
ros_foonathan_memory_vendor-1.3.1.data/data/include/foonathan_memory/foonathan/memory/error.hpp
ros_foonathan_memory_vendor-1.3.1.data/data/include/foonathan_memory/foonathan/memory/fallback_allocator.hpp
ros_foonathan_memory_vendor-1.3.1.data/data/include/foonathan_memory/foonathan/memory/heap_allocator.hpp
ros_foonathan_memory_vendor-1.3.1.data/data/include/foonathan_memory/foonathan/memory/iteration_allocator.hpp
ros_foonathan_memory_vendor-1.3.1.data/data/include/foonathan_memory/foonathan/memory/joint_allocator.hpp
ros_foonathan_memory_vendor-1.3.1.data/data/include/foonathan_memory/foonathan/memory/malloc_allocator.hpp
ros_foonathan_memory_vendor-1.3.1.data/data/include/foonathan_memory/foonathan/memory/memory_arena.hpp
ros_foonathan_memory_vendor-1.3.1.dist-info/METADATA
ros_foonathan_memory_vendor-1.3.1.dist-info/WHEEL
ros_foonathan_memory_vendor-1.3.1.dist-info/top_level.txt
ros_foonathan_memory_vendor-1.3.1.dist-info/RECORD
ros_foonathan_memory_vendor-1.3.1.dist-info/licenses/LICENSE
