Metadata-Version: 2.4
Name: ros-foonathan-memory-vendor
Version: 1.3.1
Summary: A ROS package that vendors the Foonathan Memory library, enabling custom and efficient memory allocation.
License-File: LICENSE
Dynamic: description
Dynamic: description-content-type
Dynamic: license-file
Dynamic: summary
